logo_to_square/.DS_Store
logo_to_square/__init__.py
logo_to_square/square_img_using_PIL.py
logo_to_square/img_processing_methods/__init__.py
logo_to_square/img_processing_methods/common_ops.py
logo_to_square/img_processing_methods/getdominantcolor.py
logo_to_square/img_processing_methods/opaque_ops.py
logo_to_square/img_processing_methods/transparent_ops.py
logo_to_square-1.0.9.dist-info/LICENSE.txt
logo_to_square-1.0.9.dist-info/METADATA
logo_to_square-1.0.9.dist-info/WHEEL
logo_to_square-1.0.9.dist-info/top_level.txt
logo_to_square-1.0.9.dist-info/RECORD
