Metadata-Version: 2.1
Name: logo-to-square
Version: 1.0.9
Summary: Add a short description here!
Home-page: https://github.com/pyscaffold/pyscaffold/
Author: Seshi Kiran
Author-email: seshi.kiran@gigvistas.com
License: MIT
Project-URL: Documentation, https://pyscaffold.org/
Platform: any
Classifier: Development Status :: 4 - Beta
Classifier: Programming Language :: Python
Requires-Python: >=3.8
License-File: LICENSE.txt
Requires-Dist: Pillow
Provides-Extra: testing
Requires-Dist: setuptools ; extra == 'testing'
Requires-Dist: pytest ; extra == 'testing'
Requires-Dist: pytest-cov ; extra == 'testing'
